tdfAnonymizer/__init__.py
tdfAnonymizer/anonymizer.py
tdfAnonymizer/resources/Prenoms.csv
tdfAnonymizer/resources/dict-fr-DELA.combined
tdfAnonymizer/resources/dictionnaire_1.txt
tdfAnonymizer/resources/dictionnaire_A.txt
tdfAnonymizer/resources/dictionnaire_B.txt
tdfAnonymizer/resources/dictionnaire_C.txt
tdfAnonymizer/resources/dictionnaire_D.txt
tdfAnonymizer/resources/dictionnaire_E.txt
tdfAnonymizer/resources/dictionnaire_F.txt
tdfAnonymizer/resources/dictionnaire_G.txt
tdfAnonymizer/resources/dictionnaire_H.txt
tdfAnonymizer/resources/dictionnaire_I.txt
tdfAnonymizer/resources/dictionnaire_J.txt
tdfAnonymizer/resources/dictionnaire_K.txt
tdfAnonymizer/resources/dictionnaire_L.txt
tdfAnonymizer/resources/dictionnaire_M.txt
tdfAnonymizer/resources/dictionnaire_N.txt
tdfAnonymizer/resources/dictionnaire_O.txt
tdfAnonymizer/resources/dictionnaire_P.txt
tdfAnonymizer/resources/dictionnaire_Q.txt
tdfAnonymizer/resources/dictionnaire_R.txt
tdfAnonymizer/resources/dictionnaire_S.txt
tdfAnonymizer/resources/dictionnaire_T.txt
tdfAnonymizer/resources/dictionnaire_U.txt
tdfAnonymizer/resources/dictionnaire_V.txt
tdfAnonymizer/resources/dictionnaire_W.txt
tdfAnonymizer/resources/dictionnaire_X.txt
tdfAnonymizer/resources/dictionnaire_Y.txt
tdfAnonymizer/resources/dictionnaire_Z.txt
tdfAnonymizer/resources/dictionnaire_À.txt
tdfAnonymizer/resources/dictionnaire_Â.txt
tdfAnonymizer/resources/dictionnaire_Ç.txt
tdfAnonymizer/resources/dictionnaire_È.txt
tdfAnonymizer/resources/dictionnaire_É.txt
tdfAnonymizer/resources/dictionnaire_Ê.txt
tdfAnonymizer/resources/dictionnaire_Î.txt
tdfAnonymizer/resources/dictionnaire_Ï.txt
tdfAnonymizer/resources/dictionnaire_Ô.txt
tdfAnonymizer/resources/dictionnaire_Ö.txt
tdfAnonymizer/resources/units.csv
tdfAnonymizer/resources/words.csv
tdf.labnum.tdfAnonymizer-0.985.dist-info/METADATA
tdf.labnum.tdfAnonymizer-0.985.dist-info/WHEEL
tdf.labnum.tdfAnonymizer-0.985.dist-info/top_level.txt
tdf.labnum.tdfAnonymizer-0.985.dist-info/RECORD
