Metadata-Version: 2.1
Name: tdf.labnum.tdfAnonymizer
Version: 0.985
Requires-Dist: nltk
Requires-Dist: pydantic
Requires-Dist: faker
Requires-Dist: pandas
Requires-Dist: gender-guesser
